{"type": "FeatureCollection", "features": [{"id": "0", "type": "Feature", "properties": {"label": "AOI-1"}, "geometry": {"type": "Point", "coordinates": [-5.4333844124426, 19.029808756422725]}}, {"id": "1", "type": "Feature", "properties": {"label": "AOI-2"}, "geometry": {"type": "Point", "coordinates": [14.739800591117016, 16.743447759252938]}}, {"id": "2", "type": "Feature", "properties": {"label": "AOI-3"}, "geometry": {"type": "Point", "coordinates": [-4.200848662350681, 10.140002547510269]}}, {"id": "3", "type": "Feature", "properties": {"label": "AOI-4"}, "geometry": {"type": "Point", "coordinates": [15.715459552768413, 7.159421910909535]}}]}